[{"orientation":"vertical","assembly":"hg38","layout":"linear","static":false,"zoomLimits":[1,null],"centerRadius":0.3,"spacing":10,"xOffset":0,"yOffset":0,"width":226,"height":280,"data":{"url":"https://resgen.io/api/v1/tileset_info/?d=UvVPeLHuRDiYA3qwFlm7xQ","type":"multivec","row":"sample","column":"position","value":"peak","categories":["sample 1"],"binSize":5},"mark":"bar","x":{"field":"start","type":"genomic","axis":"right","linkingId":"eb0b8084-f988-456f-9269-9336f177c826"},"xe":{"field":"end","type":"genomic"},"y":{"field":"peak","type":"quantitative","axis":"right"},"size":{"value":5},"style":{},"overlayOnPreviousTrack":false,"id":"c7b19540-3371-4660-87dc-67bdcf42ec05"},{"orientation":"vertical","assembly":"hg38","layout":"linear","static":false,"zoomLimits":[1,null],"centerRadius":0.3,"spacing":10,"xOffset":0,"yOffset":0,"width":226,"height":280,"data":{"url":"https://resgen.io/api/v1/tileset_info/?d=UvVPeLHuRDiYA3qwFlm7xQ","type":"multivec","row":"sample","column":"position","value":"peak","categories":["sample 1"]},"mark":"bar","x":{"field":"position","type":"genomic","axis":"right","linkingId":"eb0b8084-f988-456f-9269-9336f177c826"},"y":{"field":"peak","type":"quantitative","axis":"right"},"size":{"value":2},"style":{},"id":"df5fff41-0886-42e3-998a-2a8fa17c7650"}]