[{"layout":"linear","assembly":"hg38","orientation":"horizontal","static":false,"zoomLimits":[1,null],"centerRadius":0.3,"xOffset":0,"yOffset":0,"style":{},"width":280,"height":156,"data":{"url":"https://resgen.io/api/v1/tileset_info/?d=UvVPeLHuRDiYA3qwFlm7xQ","type":"multivec","row":"sample","column":"position","value":"peak","categories":["sample 1"]},"mark":"point","x":{"field":"position","type":"genomic","axis":"bottom","linkingId":"dca3a553-c62b-43d2-8919-4b72da980851"},"y":{"field":"peak","type":"quantitative","axis":"right"},"size":{"value":2},"overlayOnPreviousTrack":false,"id":"27562d64-5fea-4db2-b484-3d9f311fbc06"},{"layout":"linear","assembly":"hg38","orientation":"horizontal","static":false,"zoomLimits":[1,null],"centerRadius":0.3,"xOffset":0,"yOffset":0,"style":{},"width":280,"height":156,"data":{"url":"https://resgen.io/api/v1/tileset_info/?d=UvVPeLHuRDiYA3qwFlm7xQ","type":"multivec","row":"sample","column":"position","value":"peak","categories":["sample 1"],"binSize":5},"mark":"bar","x":{"field":"start","type":"genomic","axis":"bottom","linkingId":"57253f21-4ecb-4c74-be69-81b409b87ae0"},"xe":{"field":"end","type":"genomic"},"y":{"field":"peak","type":"quantitative","axis":"right"},"size":{"value":5},"overlayOnPreviousTrack":false,"id":"e0c5c9fe-7574-467d-8a48-375bcf8bbad1"},{"assembly":"hg38","layout":"linear","orientation":"horizontal","static":false,"zoomLimits":[1,null],"centerRadius":0.3,"xOffset":0,"yOffset":0,"style":{},"width":280,"height":156,"data":{"url":"https://resgen.io/api/v1/tileset_info/?d=UvVPeLHuRDiYA3qwFlm7xQ","type":"multivec","row":"sample","column":"position","value":"peak","categories":["sample 1"]},"mark":"line","x":{"field":"position","type":"genomic","axis":"bottom","linkingId":"b8eacc56-d28c-400b-aa8b-289331d5de8c"},"y":{"field":"peak","type":"quantitative","axis":"right"},"size":{"value":2},"overlayOnPreviousTrack":false,"id":"c9a45c9e-8c5e-4dc6-a14e-aa65138dc1fb"},{"assembly":"hg38","layout":"linear","orientation":"horizontal","static":false,"zoomLimits":[1,null],"centerRadius":0.3,"xOffset":0,"yOffset":0,"style":{},"width":280,"height":156,"data":{"url":"https://resgen.io/api/v1/tileset_info/?d=UvVPeLHuRDiYA3qwFlm7xQ","type":"multivec","row":"sample","column":"position","value":"peak","categories":["sample 1"]},"mark":"bar","x":{"field":"position","type":"genomic","axis":"bottom","linkingId":"029fd697-2fdd-417a-abd1-dddf3735f167"},"y":{"field":"peak","type":"quantitative","axis":"right"},"size":{"field":"peak","type":"quantitative"},"overlayOnPreviousTrack":false,"id":"bdc7676e-7c03-4e26-ae1f-69225c1ea0dd"}]