[{"static":true,"layout":"circular","xDomain":{"chromosome":"chr1"},"data":{"url":"https://server.gosling-lang.org/api/v1/tileset_info/?d=cistrome-multivec","type":"multivec","row":"sample","column":"position","value":"peak","categories":["sample 1","sample 2","sample 3","sample 4"]},"x":{"field":"start","type":"genomic","domain":{"chromosome":"1"},"linkingId":"076fb97a-25f3-4a80-aba1-0efa518a17f1","axis":"top"},"xe":{"field":"end","type":"genomic"},"y":{"field":"peak","type":"quantitative"},"row":{"field":"sample","type":"nominal"},"color":{"field":"sample","type":"nominal"},"width":250,"height":250,"assembly":"hg38","orientation":"horizontal","zoomLimits":[1,null],"centerRadius":0.3,"xOffset":0,"yOffset":0,"style":{},"mark":"bar","overlayOnPreviousTrack":false,"outerRadius":125,"innerRadius":37.5,"startAngle":14.4,"endAngle":345.59999999999997,"id":"f6916397-1b92-43f6-be53-4e2c9fa5e82b"},{"layout":"linear","xDomain":{"chromosome":"chr1"},"data":{"url":"https://server.gosling-lang.org/api/v1/tileset_info/?d=cistrome-multivec","type":"multivec","row":"sample","column":"position","value":"peak","categories":["sample 1","sample 2","sample 3","sample 4"]},"x":{"field":"start","type":"genomic","domain":{"chromosome":"1"},"linkingId":"b2f89fa0-29c9-4a5b-8ea5-deecc82e074f","axis":"top"},"xe":{"field":"end","type":"genomic"},"y":{"field":"peak","type":"quantitative"},"row":{"field":"sample","type":"nominal"},"color":{"field":"sample","type":"nominal"},"width":400,"height":230,"assembly":"hg38","orientation":"horizontal","static":false,"zoomLimits":[1,null],"centerRadius":0.3,"xOffset":0,"yOffset":0,"style":{},"mark":"point","overlayOnPreviousTrack":false,"id":"4531cd50-73a7-403c-b400-ed9f855b7e4c"},{"layout":"linear","xDomain":{"chromosome":"chr1","interval":[160000000,200000000]},"assembly":"hg38","orientation":"horizontal","static":false,"zoomLimits":[1,null],"centerRadius":0.3,"xOffset":0,"yOffset":0,"style":{},"data":{"url":"https://server.gosling-lang.org/api/v1/tileset_info/?d=cistrome-multivec","type":"multivec","row":"sample","column":"position","value":"peak","categories":["sample 1","sample 2","sample 3","sample 4"]},"mark":"bar","x":{"field":"position","type":"genomic","axis":"top","domain":{"chromosome":"1","interval":[160000000,200000000]},"linkingId":"2ea48a6b-26fb-4e80-940e-12f5e57c1952"},"y":{"field":"peak","type":"quantitative"},"row":{"field":"sample","type":"nominal"},"color":{"field":"sample","type":"nominal"},"width":325,"height":130,"overlayOnPreviousTrack":false,"id":"310d3650-0cff-46d4-b298-0d937d869bf8"}]