[{"layout":"linear","assembly":"hg38","orientation":"horizontal","static":false,"zoomLimits":[1,null],"centerRadius":0.3,"xOffset":0,"yOffset":0,"style":{},"width":140,"height":156,"data":{"url":"https://resgen.io/api/v1/tileset_info/?d=UvVPeLHuRDiYA3qwFlm7xQ","type":"multivec","row":"sample","column":"position","value":"peak","categories":["sample 1"],"binSize":5},"mark":"area","x":{"field":"start","type":"genomic","axis":"bottom","linkingId":"f6f99dd4-0d98-4393-8b7f-b1d84afc7b49"},"xe":{"field":"end","type":"genomic"},"y":{"field":"peak","type":"quantitative","axis":"right"},"size":{"value":5},"overlayOnPreviousTrack":false,"id":"743de177-0bfc-4f3d-87af-49d4fabfe5e4"},{"layout":"linear","assembly":"hg38","orientation":"horizontal","static":false,"zoomLimits":[1,null],"centerRadius":0.3,"xOffset":0,"yOffset":0,"style":{},"width":140,"height":156,"data":{"url":"https://resgen.io/api/v1/tileset_info/?d=UvVPeLHuRDiYA3qwFlm7xQ","type":"multivec","row":"sample","column":"position","value":"peak","categories":["sample 1"]},"mark":"bar","x":{"field":"position","type":"genomic","axis":"bottom","linkingId":"62b54c7c-20a4-4e3e-85e6-2b55f83808a8"},"y":{"field":"peak","type":"quantitative","axis":"right"},"size":{"value":2},"overlayOnPreviousTrack":false,"id":"1636edf3-a2cb-4109-8b14-bc248a42fe7d"},{"assembly":"hg38","layout":"linear","orientation":"horizontal","static":false,"zoomLimits":[1,null],"centerRadius":0.3,"xOffset":0,"yOffset":0,"style":{},"width":105,"height":156,"data":{"url":"https://resgen.io/api/v1/tileset_info/?d=UvVPeLHuRDiYA3qwFlm7xQ","type":"multivec","row":"sample","column":"position","value":"peak","categories":["sample 1"]},"mark":"area","x":{"field":"position","type":"genomic","axis":"bottom","linkingId":"6ba3b16e-2073-4e39-ad70-9fa367f96f96"},"y":{"field":"peak","type":"quantitative","axis":"right"},"size":{"field":"peak","type":"quantitative"},"overlayOnPreviousTrack":false,"id":"fa905f9b-375a-44cb-bb4a-9d610286cc85"},{"assembly":"hg38","layout":"linear","orientation":"horizontal","static":false,"zoomLimits":[1,null],"centerRadius":0.3,"xOffset":0,"yOffset":0,"style":{},"width":175,"height":156,"data":{"url":"https://resgen.io/api/v1/tileset_info/?d=UvVPeLHuRDiYA3qwFlm7xQ","type":"multivec","row":"sample","column":"position","value":"peak","categories":["sample 1"]},"mark":"area","x":{"field":"position","type":"genomic","axis":"bottom","linkingId":"3e7b65a1-6d91-4f47-b87d-7a78ae3f059e"},"y":{"field":"peak","type":"quantitative","axis":"right"},"size":{"value":2},"overlayOnPreviousTrack":false,"id":"13aa471c-16be-455c-95e6-f66f66c0c5b3"}]