[{"assembly":"hg38","layout":"linear","orientation":"horizontal","static":false,"zoomLimits":[1,null],"centerRadius":0.3,"spacing":10,"xOffset":0,"yOffset":0,"width":400,"height":390,"data":{"url":"https://resgen.io/api/v1/tileset_info/?d=UvVPeLHuRDiYA3qwFlm7xQ","type":"multivec","row":"sample","column":"position","value":"peak","categories":["sample 1"],"binSize":5},"mark":"line","x":{"field":"start","type":"genomic","axis":"bottom","linkingId":"84e0ba1b-1a31-4ba3-bc0c-53fc00eef1ae"},"xe":{"field":"end","type":"genomic"},"y":{"field":"peak","type":"quantitative","axis":"right"},"size":{"value":5},"style":{},"overlayOnPreviousTrack":false,"id":"f6e4767f-0790-4ca3-b458-5260b2ce8c21"},{"assembly":"hg38","layout":"linear","orientation":"horizontal","static":false,"zoomLimits":[1,null],"centerRadius":0.3,"spacing":10,"xOffset":0,"yOffset":0,"width":400,"height":390,"data":{"url":"https://resgen.io/api/v1/tileset_info/?d=UvVPeLHuRDiYA3qwFlm7xQ","type":"multivec","row":"sample","column":"position","value":"peak","categories":["sample 1"]},"mark":"line","x":{"field":"position","type":"genomic","axis":"bottom","linkingId":"84e0ba1b-1a31-4ba3-bc0c-53fc00eef1ae"},"y":{"field":"peak","type":"quantitative","axis":"right"},"size":{"value":2},"style":{},"id":"745b834f-f543-4b76-8e83-6f80685554a7"}]