[{"layout":"linear","assembly":"hg38","orientation":"horizontal","static":false,"zoomLimits":[1,null],"centerRadius":0.3,"xOffset":0,"yOffset":0,"style":{},"width":240,"height":246,"data":{"url":"https://resgen.io/api/v1/tileset_info/?d=UvVPeLHuRDiYA3qwFlm7xQ","type":"multivec","row":"sample","column":"position","value":"peak","categories":["sample 1"],"binSize":5},"mark":"bar","x":{"field":"start","type":"genomic","axis":"bottom","linkingId":"90c257ab-96de-44eb-b143-593332db5f53"},"xe":{"field":"end","type":"genomic"},"y":{"field":"peak","type":"quantitative","axis":"right"},"size":{"value":5},"overlayOnPreviousTrack":false,"id":"625e5849-bf67-4410-b1b2-92466f2aeb9f"},{"layout":"linear","assembly":"hg38","orientation":"horizontal","static":false,"zoomLimits":[1,null],"centerRadius":0.3,"xOffset":0,"yOffset":0,"style":{},"width":240,"height":246,"data":{"url":"https://resgen.io/api/v1/tileset_info/?d=UvVPeLHuRDiYA3qwFlm7xQ","type":"multivec","row":"sample","column":"position","value":"peak","categories":["sample 1"]},"mark":"point","x":{"field":"position","type":"genomic","axis":"bottom","linkingId":"a312db4e-ed7b-4758-bca6-62fcc994e95e"},"y":{"field":"peak","type":"quantitative","axis":"right"},"size":{"value":2},"overlayOnPreviousTrack":false,"id":"4a944192-fd7d-46f9-87af-264bec5cd00f"},{"assembly":"hg38","layout":"linear","orientation":"horizontal","static":false,"zoomLimits":[1,null],"centerRadius":0.3,"xOffset":0,"yOffset":0,"style":{},"width":180,"height":246,"data":{"url":"https://resgen.io/api/v1/tileset_info/?d=UvVPeLHuRDiYA3qwFlm7xQ","type":"multivec","row":"sample","column":"position","value":"peak","categories":["sample 1"]},"mark":"bar","x":{"field":"position","type":"genomic","axis":"bottom","linkingId":"e90781a7-9037-418b-ab9d-c64aed0789a0"},"y":{"field":"peak","type":"quantitative","axis":"right"},"size":{"field":"peak","type":"quantitative"},"overlayOnPreviousTrack":false,"id":"f8ddb88c-0e84-48f7-a0d1-1b06e3f698c4"},{"assembly":"hg38","layout":"linear","orientation":"horizontal","static":false,"zoomLimits":[1,null],"centerRadius":0.3,"xOffset":0,"yOffset":0,"style":{},"width":300,"height":246,"data":{"url":"https://resgen.io/api/v1/tileset_info/?d=UvVPeLHuRDiYA3qwFlm7xQ","type":"multivec","row":"sample","column":"position","value":"peak","categories":["sample 1"]},"mark":"point","x":{"field":"position","type":"genomic","axis":"bottom","linkingId":"f9aedb16-fe2c-4bc0-8a3b-87619d0ab329"},"y":{"field":"peak","type":"quantitative","axis":"right"},"size":{"value":2},"overlayOnPreviousTrack":false,"id":"1bff887d-e40b-409d-b433-7420986a5b21"}]