[{"layout":"linear","assembly":"hg38","orientation":"horizontal","static":false,"zoomLimits":[1,null],"centerRadius":0.3,"xOffset":0,"yOffset":0,"style":{},"width":140,"height":156,"data":{"url":"https://resgen.io/api/v1/tileset_info/?d=UvVPeLHuRDiYA3qwFlm7xQ","type":"multivec","row":"sample","column":"position","value":"peak","categories":["sample 1"],"binSize":5},"mark":"area","x":{"field":"start","type":"genomic","axis":"bottom","linkingId":"17880e3c-eacc-4d8c-b96e-fb5c5f066ff6"},"xe":{"field":"end","type":"genomic"},"y":{"field":"peak","type":"quantitative","axis":"right"},"size":{"value":5},"overlayOnPreviousTrack":false,"id":"00057419-a183-42dc-a97f-07188b91e1d1"},{"layout":"linear","assembly":"hg38","orientation":"horizontal","static":false,"zoomLimits":[1,null],"centerRadius":0.3,"xOffset":0,"yOffset":0,"style":{},"width":140,"height":156,"data":{"url":"https://resgen.io/api/v1/tileset_info/?d=UvVPeLHuRDiYA3qwFlm7xQ","type":"multivec","row":"sample","column":"position","value":"peak","categories":["sample 1"]},"mark":"point","x":{"field":"position","type":"genomic","axis":"bottom","linkingId":"353098a6-7efe-4284-96ca-6c45c938e766"},"y":{"field":"peak","type":"quantitative","axis":"right"},"size":{"value":2},"overlayOnPreviousTrack":false,"id":"17895a24-f384-4027-9492-6df5a687f698"},{"assembly":"hg38","layout":"linear","orientation":"horizontal","static":false,"zoomLimits":[1,null],"centerRadius":0.3,"xOffset":0,"yOffset":0,"style":{},"width":105,"height":156,"data":{"url":"https://resgen.io/api/v1/tileset_info/?d=UvVPeLHuRDiYA3qwFlm7xQ","type":"multivec","row":"sample","column":"position","value":"peak","categories":["sample 1"]},"mark":"area","x":{"field":"position","type":"genomic","axis":"bottom","linkingId":"2ad8ee09-2702-40a0-a12d-0836d351f66a"},"y":{"field":"peak","type":"quantitative","axis":"right"},"size":{"field":"peak","type":"quantitative"},"overlayOnPreviousTrack":false,"id":"0df8d9f6-0d06-4d9c-baf5-7854d8c7f3d0"},{"assembly":"hg38","layout":"linear","orientation":"horizontal","static":false,"zoomLimits":[1,null],"centerRadius":0.3,"xOffset":0,"yOffset":0,"style":{},"width":175,"height":156,"data":{"url":"https://resgen.io/api/v1/tileset_info/?d=UvVPeLHuRDiYA3qwFlm7xQ","type":"multivec","row":"sample","column":"position","value":"peak","categories":["sample 1"]},"mark":"line","x":{"field":"position","type":"genomic","axis":"bottom","linkingId":"42f4c5c1-5ff8-4f29-8d81-46749e2f0caf"},"y":{"field":"peak","type":"quantitative","axis":"right"},"size":{"value":2},"overlayOnPreviousTrack":false,"id":"83434ce9-64d3-4bdf-bb7c-8c258b86076b"}]