[{"layout":"linear","assembly":"hg38","orientation":"horizontal","static":false,"zoomLimits":[1,null],"centerRadius":0.3,"xOffset":0,"yOffset":0,"style":{},"width":280,"height":210,"data":{"url":"https://resgen.io/api/v1/tileset_info/?d=UvVPeLHuRDiYA3qwFlm7xQ","type":"multivec","row":"sample","column":"position","value":"peak","categories":["sample 1"],"binSize":5},"mark":"line","x":{"field":"start","type":"genomic","axis":"bottom","linkingId":"e2648643-1f97-4de1-ab4f-2409d1176f95"},"xe":{"field":"end","type":"genomic"},"y":{"field":"peak","type":"quantitative","axis":"right"},"size":{"value":5},"overlayOnPreviousTrack":false,"id":"f36b9af2-978d-44bf-bc09-a240b485bfaa"},{"layout":"linear","assembly":"hg38","orientation":"horizontal","static":false,"zoomLimits":[1,null],"centerRadius":0.3,"xOffset":0,"yOffset":0,"style":{},"width":280,"height":210,"data":{"url":"https://resgen.io/api/v1/tileset_info/?d=UvVPeLHuRDiYA3qwFlm7xQ","type":"multivec","row":"sample","column":"position","value":"peak","categories":["sample 1"]},"mark":"area","x":{"field":"position","type":"genomic","axis":"bottom","linkingId":"b4fbbae8-6dc8-48b9-85ce-e3460f150111"},"y":{"field":"peak","type":"quantitative","axis":"right"},"size":{"value":2},"overlayOnPreviousTrack":false,"id":"2343c38f-6020-430c-8e80-192ce4c7c9b0"},{"assembly":"hg38","layout":"linear","orientation":"horizontal","static":false,"zoomLimits":[1,null],"centerRadius":0.3,"xOffset":0,"yOffset":0,"style":{},"width":210,"height":210,"data":{"url":"https://resgen.io/api/v1/tileset_info/?d=UvVPeLHuRDiYA3qwFlm7xQ","type":"multivec","row":"sample","column":"position","value":"peak","categories":["sample 1"]},"mark":"bar","x":{"field":"position","type":"genomic","axis":"bottom","linkingId":"d8823a9d-3aba-4dc9-9cfe-a15aeba58505"},"y":{"field":"peak","type":"quantitative","axis":"right"},"size":{"field":"peak","type":"quantitative"},"overlayOnPreviousTrack":false,"id":"551209ab-ae7e-47a0-a68a-036066a19446"},{"assembly":"hg38","layout":"linear","orientation":"horizontal","static":false,"zoomLimits":[1,null],"centerRadius":0.3,"xOffset":0,"yOffset":0,"style":{},"width":350,"height":210,"data":{"url":"https://resgen.io/api/v1/tileset_info/?d=UvVPeLHuRDiYA3qwFlm7xQ","type":"multivec","row":"sample","column":"position","value":"peak","categories":["sample 1"]},"mark":"bar","x":{"field":"position","type":"genomic","axis":"bottom","linkingId":"5ed3fd11-9490-4ded-bb8e-cc1359e4bb4c"},"y":{"field":"peak","type":"quantitative","axis":"right"},"size":{"value":2},"overlayOnPreviousTrack":false,"id":"bb5bec61-4db4-433e-8934-cc34351aac23"}]